odoo/addons/purchase_incoming_products/README.rst
odoo/addons/purchase_incoming_products/__init__.py
odoo/addons/purchase_incoming_products/__manifest__.py
odoo/addons/purchase_incoming_products/i18n/es_MX.po
odoo/addons/purchase_incoming_products/i18n/purchase_incoming_products.pot
odoo/addons/purchase_incoming_products/readme/CONTRIBUTORS.rst
odoo/addons/purchase_incoming_products/readme/DESCRIPTION.rst
odoo/addons/purchase_incoming_products/readme/USAGE.rst
odoo/addons/purchase_incoming_products/static/description/icon.png
odoo/addons/purchase_incoming_products/static/description/index.html
odoo/addons/purchase_incoming_products/views/purchase_incoming_products.xml
odoo13_addon_purchase_incoming_products-13.0.1.0.1.dev7.dist-info/METADATA
odoo13_addon_purchase_incoming_products-13.0.1.0.1.dev7.dist-info/WHEEL
odoo13_addon_purchase_incoming_products-13.0.1.0.1.dev7.dist-info/top_level.txt
odoo13_addon_purchase_incoming_products-13.0.1.0.1.dev7.dist-info/RECORD
